TCLIService/TCLIService.py
TCLIService/__init__.py
TCLIService/constants.py
TCLIService/ttypes.py
pyhive/__init__.py
pyhive/common.py
pyhive/exc.py
pyhive/hive.py
pyhive/presto.py
pyhive/sqlalchemy_hive.py
pyhive/sqlalchemy_presto.py
pyhive/sqlalchemy_trino.py
pyhive/trino.py
pyhive_fix-0.6.3.dev0.dist-info/LICENSE
pyhive_fix-0.6.3.dev0.dist-info/METADATA
pyhive_fix-0.6.3.dev0.dist-info/WHEEL
pyhive_fix-0.6.3.dev0.dist-info/entry_points.txt
pyhive_fix-0.6.3.dev0.dist-info/top_level.txt
pyhive_fix-0.6.3.dev0.dist-info/RECORD
